qtcolor/__init__.py
qtcolor/test.py
qtcolor-4.3.dist-info/METADATA
qtcolor-4.3.dist-info/WHEEL
qtcolor-4.3.dist-info/top_level.txt
qtcolor-4.3.dist-info/RECORD
