Metadata-Version: 2.1
Name: qtcolor
Version: 4.3
Summary: Make Your Code colrful
Author-email: qtdev@gmail.com
License: Eclipse Public License 2.0
